LICENSE
README.md
pyproject.toml
setup.py
src/Humre.egg-info/PKG-INFO
src/Humre.egg-info/SOURCES.txt
src/Humre.egg-info/dependency_links.txt
src/Humre.egg-info/top_level.txt
src/humre/__init__.py