Metadata-Version: 2.1
Name: Humre
Version: 1.0.0
Summary: A human-readable regular expression module for Python. Humre handles regex syntax for you and creates regex strings to pass to Python's re.compile(). Pronounced "hum, ree".
Home-page: https://github.com/asweigart/humre
Author: Al Sweigart
Author-email: Al Sweigart <al@inventwithpython.com>
License: Copyright (c) 2022 Al Sweigart
Project-URL: Homepage, https://github.com/asweigart/humre
Project-URL: Bug Tracker, https://github.com/asweigart/humre/issues
Keywords: regex,re,regular expression
Platform: UNKNOWN
Classifier: License :: OSI Approved :: GNU General Public License v3 or later (GPLv3+)
Classifier: Programming Language :: Python
Classifier: Programming Language :: Python :: 3
Classifier: Programming Language :: Python :: 3.5
Classifier: Programming Language :: Python :: 3.6
Classifier: Programming Language :: Python :: 3.7
Classifier: Programming Language :: Python :: 3.8
Classifier: Programming Language :: Python :: 3.9
Classifier: Programming Language :: Python :: 3.10
Classifier: Programming Language :: Python :: 3.11
Classifier: Programming Language :: Python :: 3.12
Requires-Python: >=3.5
License-File: LICENSE
